gwax/__init__.py
gwax/flows.py
gwax/likelihood.py
gwax/parametric.py
gwax/remnant.py
gwax/variational.py
gwax-0.1.0.dist-info/licenses/LICENSE
gwax-0.1.0.dist-info/METADATA
gwax-0.1.0.dist-info/WHEEL
gwax-0.1.0.dist-info/top_level.txt
gwax-0.1.0.dist-info/RECORD
