Metadata-Version: 2.4
Name: gwax
Version: 0.1.0
Summary: Gravitational-wave astronomy in JAX
Author-email: Matthew Mould <mattdmould@gmail.com>
Project-URL: Homepage, https://github.com/mdmould/gwax
Classifier: Programming Language :: Python :: 3
Classifier: License :: OSI Approved :: MIT License
Classifier: Operating System :: OS Independent
Requires-Python: >=3.11
License-File: LICENSE
Requires-Dist: jax
Requires-Dist: jax_tqdm
Requires-Dist: equinox
Requires-Dist: optax
Requires-Dist: flowjax
Requires-Dist: numpyro
Requires-Dist: bilby
Requires-Dist: wcosmo
Dynamic: license-file
